bert_deid/BERT_CRF.py
bert_deid/__init__.py
bert_deid/__main__.py
bert_deid/datasets.py
bert_deid/download.py
bert_deid/ensemble_feature.py
bert_deid/extra_feature_crf.py
bert_deid/label.py
bert_deid/processors.py
bert_deid/pydeid_feature.py
bert_deid/tokenization.py
bert_deid/utils.py
bert_deid/model/__init__.py
bert_deid/model/albert.py
bert_deid/model/crf.py
bert_deid/model/extra_feature.py
bert_deid/model/transformer.py
bert_deid-0.2.3.dist-info/METADATA
bert_deid-0.2.3.dist-info/WHEEL
bert_deid-0.2.3.dist-info/entry_points.txt
bert_deid-0.2.3.dist-info/top_level.txt
bert_deid-0.2.3.dist-info/RECORD
