Metadata-Version: 2.1
Name: bert-deid
Version: 0.2.3
Summary: Remove identifiers from data using BERT
Home-page: https://github.com/alistairewj/bert-deid
Author: Alistair Johnson
Author-email: aewj@mit.edu
License: Apache 2.0
Platform: UNKNOWN
Requires-Python: >=3.6
Requires-Dist: nltk (>=3.4.5)
Requires-Dist: mpmath (>=1.1.0)
Requires-Dist: numpy (>=1.19.2)
Requires-Dist: pandas (>=1.1.3)
Requires-Dist: pytest (>=4.2.0)
Requires-Dist: pytorch (>=1.6.0)
Requires-Dist: scikit-learn (>=0.23.2)
Requires-Dist: spacy (>=2.3.2)
Requires-Dist: sympy (>=1.6.2)
Requires-Dist: tqdm (>=4.32.1)
Requires-Dist: regex (>=2020.10.23)
Requires-Dist: transformers (>=3.4.0)
Requires-Dist: tokenizers (>=0.9.2)
Requires-Dist: stanfordnlp (>=0.2.0)
Requires-Dist: google-cloud-storage (>=1.32.0)
